angou_bitmex/__init__.py
angou_bitmex/auth_utils.py
angou_bitmex/rest.py
angou_bitmex-2.dist-info/LICENSE.txt
angou_bitmex-2.dist-info/METADATA
angou_bitmex-2.dist-info/RECORD
angou_bitmex-2.dist-info/WHEEL
angou_bitmex-2.dist-info/top_level.txt
